oneNeuron/__init__.py
oneNeuron/perceptron.py
oneNeuron_PyPi_bapatlaayyanna-0.0.1.dist-info/LICENSE
oneNeuron_PyPi_bapatlaayyanna-0.0.1.dist-info/METADATA
oneNeuron_PyPi_bapatlaayyanna-0.0.1.dist-info/WHEEL
oneNeuron_PyPi_bapatlaayyanna-0.0.1.dist-info/top_level.txt
oneNeuron_PyPi_bapatlaayyanna-0.0.1.dist-info/RECORD
